control_plotly/__init__.py
control_plotly/figures.py
control_plotly/grid.py
control_plotly/plots.py
control_plotly/utils.py
control_plotly-0.2.0.dist-info/LICENCE
control_plotly-0.2.0.dist-info/METADATA
control_plotly-0.2.0.dist-info/WHEEL
control_plotly-0.2.0.dist-info/top_level.txt
control_plotly-0.2.0.dist-info/RECORD
