Metadata-Version: 2.1
Name: control-plotly
Version: 0.2.0
Summary: A plotting library for the analysis of continuous and discrete time systems
Home-page: https://github.com/vincentchoqueuse/python-control-plotly
Author: Vincent Choqueuse
Author-email: vincent.choqueuse@gmail.com
License: MIT
Classifier: License :: OSI Approved :: MIT License
Classifier: Programming Language :: Python :: 3
Classifier: Programming Language :: Python :: 3.7
Classifier: Programming Language :: Python :: 3.8
License-File: LICENCE
Requires-Dist: control
Requires-Dist: plotly
